{
	"credit": "Made with Blockbench",
	"textures": {
		"0": "fumofumo:item/gohei",
		"particle": "fumofumo:item/gohei"
	},
	"elements": [
		{
			"name": "palka",
			"from": [7, 0, 7],
			"to": [9, 14, 9],
			"faces": {
				"north": {"uv": [14, 0, 16, 14], "texture": "#0"},
				"east": {"uv": [14, 0, 16, 14], "texture": "#0"},
				"south": {"uv": [14, 0, 16, 14], "texture": "#0"},
				"west": {"uv": [14, 0, 16, 14], "texture": "#0"},
				"up": {"uv": [14, 0, 16, 2], "texture": "#0"},
				"down": {"uv": [14, 0, 16, 2], "texture": "#0"}
			}
		},
		{
			"name": "obodok",
			"from": [6.75, 10, 6.75],
			"to": [9.25, 12, 9.25],
			"faces": {
				"north": {"uv": [13.5, 14, 16, 16], "texture": "#0"},
				"east": {"uv": [1, 14, 3.5, 16], "texture": "#0"},
				"south": {"uv": [3.5, 14, 6, 16], "texture": "#0"},
				"west": {"uv": [6, 14, 8.5, 16], "texture": "#0"},
				"up": {"uv": [8.5, 13.5, 11, 16], "texture": "#0"},
				"down": {"uv": [11, 13.5, 13.5, 16], "texture": "#0"}
			}
		},
		{
			"name": "list1",
			"from": [9.62317, 8.12396, 4.75],
			"to": [9.87317, 10.12396, 6.75],
			"rotation": {"angle": 22.5, "axis": "z", "origin": [9.74817, 9.12396, 5.75]},
			"faces": {
				"north": {"uv": [0, 0, 0.25, 2], "rotation": 180, "texture": "#0"},
				"east": {"uv": [0, 0, 2, 2], "rotation": 180, "texture": "#0"},
				"south": {"uv": [0, 0, 0.25, 2], "rotation": 180, "texture": "#0"},
				"west": {"uv": [0, 0, 2, 2], "rotation": 180, "texture": "#0"},
				"up": {"uv": [0, 0, 2, 0.25], "rotation": 90, "texture": "#0"},
				"down": {"uv": [0, 0, 2, 0.25], "rotation": 270, "texture": "#0"}
			}
		},
		{
			"name": "list2",
			"from": [6.00628, 8.2045, 9.25],
			"to": [6.25628, 10.2045, 11.25],
			"rotation": {"angle": -45, "axis": "z", "origin": [6.13128, 9.2045, 10.25]},
			"faces": {
				"north": {"uv": [0, 0, 0.25, 2], "texture": "#0"},
				"east": {"uv": [0, 0, 2, 2], "texture": "#0"},
				"south": {"uv": [0, 0, 0.25, 2], "texture": "#0"},
				"west": {"uv": [0, 0, 2, 2], "texture": "#0"},
				"up": {"uv": [0, 0, 2, 0.25], "rotation": 90, "texture": "#0"},
				"down": {"uv": [0, 0, 2, 0.25], "rotation": 270, "texture": "#0"}
			}
		},
		{
			"name": "list3",
			"from": [10.01537, 6.18053, 4.3578],
			"to": [12.01537, 8.18053, 4.6078],
			"rotation": {"angle": 22.5, "axis": "x", "origin": [11.01537, 7.18053, 4.4828]},
			"faces": {
				"north": {"uv": [0, 0, 2, 2], "rotation": 90, "texture": "#0"},
				"east": {"uv": [0, 0, 2, 0.25], "rotation": 270, "texture": "#0"},
				"south": {"uv": [0, 0, 2, 2], "rotation": 270, "texture": "#0"},
				"west": {"uv": [0, 0, 2, 0.25], "rotation": 270, "texture": "#0"},
				"up": {"uv": [0, 0, 0.25, 2], "rotation": 270, "texture": "#0"},
				"down": {"uv": [0, 0, 0.25, 2], "rotation": 270, "texture": "#0"}
			}
		},
		{
			"name": "list4",
			"from": [4.94359, 6.61407, 11.25],
			"to": [5.19359, 8.61407, 13.25],
			"rotation": {"angle": -22.5, "axis": "z", "origin": [5.06859, 7.61407, 12.25]},
			"faces": {
				"north": {"uv": [2, 2, 3, 4], "texture": "#0"},
				"east": {"uv": [0, 2, 2, 4], "texture": "#0"},
				"south": {"uv": [2, 0, 3, 2], "texture": "#0"},
				"west": {"uv": [0, 0, 2, 2], "texture": "#0"},
				"up": {"uv": [4, 2, 3, 0], "rotation": 180, "texture": "#0"},
				"down": {"uv": [4, 2, 3, 4], "rotation": 180, "texture": "#0"}
			}
		}
	],
	"display": {
		"thirdperson_righthand": {
			"rotation": [-2, -25, 0],
			"translation": [0.25, 6.25, 0.75],
			"scale": [0.6, 0.97, 0.6]
		},
		"thirdperson_lefthand": {
			"rotation": [-2, -131, 0],
			"translation": [0.25, 6.25, 0.75],
			"scale": [0.6, 0.97, 0.6]
		},
		"firstperson_righthand": {
			"rotation": [-8, -24, 3],
			"translation": [0.25, 6.25, 0.75],
			"scale": [0.6, 0.97, 0.6]
		},
		"firstperson_lefthand": {
			"rotation": [-11, 19, -3],
			"translation": [2.25, 3.25, 0],
			"scale": [0.6, 0.97, 0.6]
		},
		"ground": {
			"rotation": [-2, -25, 0],
			"translation": [0.25, 4.25, 0.75],
			"scale": [0.6, 0.97, 0.6]
		},
		"gui": {
			"rotation": [20, -39, 31],
			"translation": [0.25, 1, 0.75],
			"scale": [0.6, 0.97, 0.6]
		},
		"head": {
			"rotation": [129, -25, 0],
			"translation": [0.25, 3, -4.5],
			"scale": [0.6, 0.97, 0.6]
		},
		"fixed": {
			"rotation": [-2, -46, 0],
			"translation": [-0.25, -0.25, 0],
			"scale": [0.6, 0.97, 0.6]
		}
	}
}